umbitlib/__init__.py
umbitlib/constants.py
umbitlib/database/__init__.py
umbitlib/database/config_loader.py
umbitlib/database/credential_provider.py
umbitlib/database/db_interactions.py
umbitlib/database/engine_creator.py
umbitlib/database/engine_factories.py
umbitlib/database/README.md
umbitlib/database/sql_handler.py
umbitlib/database/utils.py
umbitlib/dates.py
umbitlib/db_connections.py
umbitlib/graphs.py
umbitlib/helpers.py
umbitlib/queries.py
umbitlib/science.py
umbitlib-0.0.80.dist-info/LICENSE
umbitlib-0.0.80.dist-info/METADATA
umbitlib-0.0.80.dist-info/WHEEL
umbitlib-0.0.80.dist-info/RECORD
